{"version": "V2", "requestId": "12eb9e11-dc20-4869-b47e-e48a90c2c916", "timestamp": 1679640354410, "images": [{"uid": "0b168450b7124a318c9b94ea50d5dbe8", "name": "demo", "inferResult": "SUCCESS", "message": "SUCCESS", "validationResult": {"result": "NO_REQUESTED"}, "convertedImageInfo": {"width": 1080, "height": 1440, "pageIndex": 0, "longImage": false}, "fields": [{"valueType": "ALL", "boundingPoly": {"vertices": [{"x": 215.0, "y": 363.0}, {"x": 475.0, "y": 369.0}, {"x": 474.0, "y": 414.0}, {"x": 214.0, "y": 408.0}]}, "inferText": "[\uc8fc\ubb38(\ub300\uae30)\ubc88\ud638]", "inferConfidence": 0.999, "type": "NORMAL", "lineBreak": true}, {"valueType": "ALL", "boundingPoly": {"vertices": [{"x": 502.0, "y": 408.0}, {"x": 608.0, "y": 410.0}, {"x": 607.0, "y": 473.0}, {"x": 500.0, "y": 470.0}]}, "inferText": "291", "inferConfidence": 0.9998, "type": "NORMAL", "lineBreak": true}, {"valueType": "ALL", "boundingPoly": {"vertices": [{"x": 208.0, "y": 541.0}, {"x": 345.0, "y": 541.0}, {"x": 345.0, "y": 589.0}, {"x": 208.0, "y": 589.0}]}, "inferText": "\uc8fc\ubb38\ub0b4\uc5ed", "inferConfidence": 0.9999, "type": "NORMAL", "lineBreak": true}, {"valueType": "ALL", "boundingPoly": {"vertices": [{"x": 354.0, "y": 582.0}, {"x": 458.0, "y": 582.0}, {"x": 458.0, "y": 629.0}, {"x": 354.0, "y": 629.0}]}, "inferText": "\uc0c1\ud488\uba85", "inferConfidence": 0.9999, "type": "NORMAL", "lineBreak": false}, {"valueType": "ALL", "boundingPoly": {"vertices": [{"x": 714.0, "y": 584.0}, {"x": 789.0, "y": 584.0}, {"x": 789.0, "y": 625.0}, {"x": 714.0, "y": 625.0}]}, "inferText": "\uc218\ub7c9", "inferConfidence": 1.0, "type": "NORMAL", "lineBreak": false}, {"valueType": "ALL", "boundingPoly": {"vertices": [{"x": 830.0, "y": 588.0}, {"x": 904.0, "y": 591.0}, {"x": 902.0, "y": 629.0}, {"x": 828.0, "y": 626.0}]}, "inferText": "\uad6c\ubd84", "inferConfidence": 1.0, "type": "NORMAL", "lineBreak": true}, {"valueType": "ALL", "boundingPoly": {"vertices": [{"x": 206.0, "y": 621.0}, {"x": 522.0, "y": 622.0}, {"x": 522.0, "y": 667.0}, {"x": 206.0, "y": 665.0}]}, "inferText": "[\ud3ec\uc7a5](ICE)\ub538\uae30\ub77c\ub5bc", "inferConfidence": 0.999, "type": "NORMAL", "lineBreak": false}, {"valueType": "ALL", "boundingPoly": {"vertices": [{"x": 764.0, "y": 624.0}, {"x": 789.0, "y": 624.0}, {"x": 789.0, "y": 657.0}, {"x": 764.0, "y": 657.0}]}, "inferText": "3", "inferConfidence": 1.0, "type": "NORMAL", "lineBreak": false}, {"valueType": "ALL", "boundingPoly": {"vertices": [{"x": 834.0, "y": 622.0}, {"x": 906.0, "y": 622.0}, {"x": 906.0, "y": 663.0}, {"x": 834.0, "y": 663.0}]}, "inferText": "\uc2e0\uaddc", "inferConfidence": 1.0, "type": "NORMAL", "lineBreak": true}, {"valueType": "ALL", "boundingPoly": {"vertices": [{"x": 201.0, "y": 741.0}, {"x": 373.0, "y": 741.0}, {"x": 373.0, "y": 787.0}, {"x": 201.0, "y": 787.0}]}, "inferText": "\ucd1d\uc8fc\ubb38\uae08\uc561", "inferConfidence": 0.9994, "type": "NORMAL", "lineBreak": false}, {"valueType": "ALL", "boundingPoly": {"vertices": [{"x": 750.0, "y": 746.0}, {"x": 864.0, "y": 746.0}, {"x": 864.0, "y": 787.0}, {"x": 750.0, "y": 787.0}]}, "inferText": "11,100", "inferConfidence": 1.0, "type": "NORMAL", "lineBreak": false}, {"valueType": "ALL", "boundingPoly": {"vertices": [{"x": 872.0, "y": 743.0}, {"x": 910.0, "y": 743.0}, {"x": 910.0, "y": 788.0}, {"x": 872.0, "y": 788.0}]}, "inferText": "\uc6d0", "inferConfidence": 0.9999, "type": "NORMAL", "lineBreak": true}, {"valueType": "ALL", "boundingPoly": {"vertices": [{"x": 579.0, "y": 869.0}, {"x": 760.0, "y": 871.0}, {"x": 760.0, "y": 911.0}, {"x": 578.0, "y": 909.0}]}, "inferText": "2023-03-21", "inferConfidence": 0.9998, "type": "NORMAL", "lineBreak": false}, {"valueType": "ALL", "boundingPoly": {"vertices": [{"x": 771.0, "y": 872.0}, {"x": 827.0, "y": 872.0}, {"x": 827.0, "y": 910.0}, {"x": 771.0, "y": 910.0}]}, "inferText": "15:", "inferConfidence": 1.0, "type": "NORMAL", "lineBreak": false}, {"valueType": "ALL", "boundingPoly": {"vertices": [{"x": 823.0, "y": 873.0}, {"x": 882.0, "y": 873.0}, {"x": 882.0, "y": 910.0}, {"x": 823.0, "y": 910.0}]}, "inferText": "00:", "inferConfidence": 0.9997, "type": "NORMAL", "lineBreak": false}, {"valueType": "ALL", "boundingPoly": {"vertices": [{"x": 876.0, "y": 872.0}, {"x": 923.0, "y": 872.0}, {"x": 923.0, "y": 912.0}, {"x": 876.0, "y": 912.0}]}, "inferText": "24", "inferConfidence": 1.0, "type": "NORMAL", "lineBreak": true}]}]}